hack4u/__init__.py
hack4u/courses.py
hack4u/utils.py
TestHack4u-1.0.1.dist-info/METADATA
TestHack4u-1.0.1.dist-info/WHEEL
TestHack4u-1.0.1.dist-info/top_level.txt
TestHack4u-1.0.1.dist-info/RECORD
