Metadata-Version: 2.1
Name: TestHack4u
Version: 1.0.1
Summary: Una biblioteca para consultar todos los cursos existentes de hack4u
Home-page: https://hack4u.io
Author: 1FeeirG
